phml/__init__.py
phml/builder.py
phml/core/__init__.py
phml/core/compiler.py
phml/core/core.py
phml/core/parser.py
phml/core/formats/__init__.py
phml/core/formats/format.py
phml/core/formats/html_format.py
phml/core/formats/json_format.py
phml/core/formats/parse.py
phml/core/formats/phml_format.py
phml/core/formats/xml_format.py
phml/core/formats/compile/__init__.py
phml/core/formats/compile/compile.py
phml/core/formats/compile/component.py
phml/core/formats/compile/reserved.py
phml/core/nodes/AST.py
phml/core/nodes/__init__.py
phml/core/nodes/nodes.py
phml/core/nodes/types.py
phml/core/virtual_python/__init__.py
phml/core/virtual_python/built_in.py
phml/core/virtual_python/import_objects.py
phml/core/virtual_python/vp.py
phml/utilities/__init__.py
phml/utilities/locate/__init__.py
phml/utilities/locate/find.py
phml/utilities/locate/index.py
phml/utilities/locate/select.py
phml/utilities/misc/__init__.py
phml/utilities/misc/classes.py
phml/utilities/misc/component.py
phml/utilities/misc/heading.py
phml/utilities/misc/inspect.py
phml/utilities/transform/__init__.py
phml/utilities/transform/extract.py
phml/utilities/transform/transform.py
phml/utilities/transform/sanitize/__init__.py
phml/utilities/transform/sanitize/clean.py
phml/utilities/transform/sanitize/schema.py
phml/utilities/travel/__init__.py
phml/utilities/travel/travel.py
phml/utilities/validate/__init__.py
phml/utilities/validate/check.py
phml/utilities/validate/validate.py
phml-2.0.0.dist-info/METADATA
phml-2.0.0.dist-info/WHEEL
phml-2.0.0.dist-info/licenses/LICENSE
phml-2.0.0.dist-info/RECORD
