Metadata-Version: 2.1
Name: phml
Version: 2.0.0
Summary: Python Hypertext Markup Language - Extension of HTML
Project-URL: Homepage, https://github.com/Tired-Fox/phml
Project-URL: Website, https://tired-fox.github.io/phml/
Author-email: Tired Fox <zboehm104@gmail.com>
License-Expression: MIT
License-File: LICENSE
Requires-Python: >=3.10
Requires-Dist: defusedxml
Requires-Dist: markdown2
Requires-Dist: saimll>=0.3.0
Provides-Extra: tests
Requires-Dist: pytest; extra == 'tests'
